{
  "generatedAt": "2026-06-25T02:00:52.089Z",
  "basis": "copyable return (from disclosure date)",
  "totals": {
    "positions": 16435,
    "priced": 12730,
    "open": 10200,
    "unpriced": 3705,
    "avgReturn": 0.5044324660810912,
    "spyAvgReturn": 0.44242500599069745
  },
  "perMember": [
    {
      "member": "Brian Higgins",
      "positions": 1,
      "avgReturn": 9.137544574630668
    },
    {
      "member": "David Cheston Rouzer",
      "positions": 2,
      "avgReturn": 4.689172863949521
    },
    {
      "member": "Ashley Moody",
      "positions": 3,
      "avgReturn": 4.424118962344632
    },
    {
      "member": "Ron L Wyden",
      "positions": 139,
      "avgReturn": 3.5030239582250173
    },
    {
      "member": "Sheldon Whitehouse",
      "positions": 49,
      "avgReturn": 2.8806029679151526
    },
    {
      "member": "Christopher A Coons",
      "positions": 2,
      "avgReturn": 2.585052631578947
    },
    {
      "member": "Michael Fq San Nicolas",
      "positions": 1,
      "avgReturn": 2.5086047940995697
    },
    {
      "member": "Susan W. Brooks",
      "positions": 12,
      "avgReturn": 2.24151347298541
    },
    {
      "member": "Susan A. Davis",
      "positions": 7,
      "avgReturn": 2.1233235320836563
    },
    {
      "member": "Susan M Collins",
      "positions": 7,
      "avgReturn": 2.0313647735301172
    },
    {
      "member": "Michael T. McCaul",
      "positions": 80,
      "avgReturn": 1.8732123859545138
    },
    {
      "member": "Debbie Wasserman Schultz",
      "positions": 5,
      "avgReturn": 1.8219103463510031
    },
    {
      "member": "Seth Moulton",
      "positions": 1,
      "avgReturn": 1.6067653276955602
    },
    {
      "member": "John Hoeven",
      "positions": 18,
      "avgReturn": 1.601453247875784
    },
    {
      "member": "Kelly Loeffler",
      "positions": 67,
      "avgReturn": 1.5567242390863385
    },
    {
      "member": "Thomas Suozzi",
      "positions": 39,
      "avgReturn": 1.55127716855353
    },
    {
      "member": "Deborah K. Ross",
      "positions": 14,
      "avgReturn": 1.536940543588732
    },
    {
      "member": "Dean Phillips",
      "positions": 189,
      "avgReturn": 1.485098959155024
    },
    {
      "member": "Greg Gianforte",
      "positions": 103,
      "avgReturn": 1.435964416608573
    },
    {
      "member": "Peter Meijer",
      "positions": 14,
      "avgReturn": 1.435945761005916
    },
    {
      "member": "Daniel Meuser",
      "positions": 1,
      "avgReturn": 1.4229879459393646
    },
    {
      "member": "Mark Green",
      "positions": 217,
      "avgReturn": 1.3984868970499926
    },
    {
      "member": "David E. Price",
      "positions": 6,
      "avgReturn": 1.2822869815409954
    },
    {
      "member": "Neal Patrick MD, Facs Dunn",
      "positions": 2,
      "avgReturn": 1.268165210195097
    },
    {
      "member": "Michael K. Simpson",
      "positions": 4,
      "avgReturn": 1.2420310472082188
    },
    {
      "member": "David A Perdue , Jr",
      "positions": 179,
      "avgReturn": 1.2028447773441762
    },
    {
      "member": "Kurt Schrader",
      "positions": 145,
      "avgReturn": 1.1786148264070446
    },
    {
      "member": "Kenny Marchant",
      "positions": 34,
      "avgReturn": 1.1169350619057536
    },
    {
      "member": "Pete Sessions",
      "positions": 60,
      "avgReturn": 1.1156503439192798
    },
    {
      "member": "Dwight Evans",
      "positions": 40,
      "avgReturn": 1.0941818134547858
    },
    {
      "member": "Victoria Spartz",
      "positions": 19,
      "avgReturn": 1.0780912157026055
    },
    {
      "member": "Trey Hollingsworth",
      "positions": 9,
      "avgReturn": 1.0556650667060121
    },
    {
      "member": "Bob Gibbs",
      "positions": 25,
      "avgReturn": 1.02557872804607
    },
    {
      "member": "A. Mitchell McConnell, Jr.",
      "positions": 31,
      "avgReturn": 1.0165373380892748
    },
    {
      "member": "John A. Yarmuth",
      "positions": 31,
      "avgReturn": 0.9832969250652775
    },
    {
      "member": "Michael Waltz",
      "positions": 2,
      "avgReturn": 0.9579286675085728
    },
    {
      "member": "Robert B. Aderholt",
      "positions": 1,
      "avgReturn": 0.9482815927674
    },
    {
      "member": "Garret Graves",
      "positions": 4,
      "avgReturn": 0.9291548621616712
    },
    {
      "member": "Stephen F. Lynch",
      "positions": 1,
      "avgReturn": 0.9204786720710287
    },
    {
      "member": "K. Michael Conaway",
      "positions": 54,
      "avgReturn": 0.9160514650284738
    },
    {
      "member": "Pat Roberts",
      "positions": 110,
      "avgReturn": 0.902355862037768
    },
    {
      "member": "Billy Long",
      "positions": 1,
      "avgReturn": 0.8615345528455285
    },
    {
      "member": "David B. McKinley",
      "positions": 60,
      "avgReturn": 0.8510774603569545
    },
    {
      "member": "Mike Kelly",
      "positions": 6,
      "avgReturn": 0.7958261849328035
    },
    {
      "member": "David P. Roe",
      "positions": 13,
      "avgReturn": 0.7881849259521891
    },
    {
      "member": "Nancy Pelosi",
      "positions": 72,
      "avgReturn": 0.7787382458134601
    },
    {
      "member": "Diana Harshbarger",
      "positions": 6,
      "avgReturn": 0.7730669254971598
    },
    {
      "member": "Susie Lee",
      "positions": 211,
      "avgReturn": 0.7724828694214285
    },
    {
      "member": "Morgan McGarvey",
      "positions": 8,
      "avgReturn": 0.7425932083507618
    },
    {
      "member": "Marjorie Taylor Greene",
      "positions": 440,
      "avgReturn": 0.7395595245313463
    },
    {
      "member": "Carol Devine Miller",
      "positions": 42,
      "avgReturn": 0.731824238353738
    },
    {
      "member": "Francis Rooney",
      "positions": 13,
      "avgReturn": 0.7312299341509075
    },
    {
      "member": "Ed Perlmutter",
      "positions": 20,
      "avgReturn": 0.7159465636400428
    },
    {
      "member": "Tina Smith",
      "positions": 5,
      "avgReturn": 0.7015068618984495
    },
    {
      "member": "Daniel S Sullivan",
      "positions": 24,
      "avgReturn": 0.687131079412738
    },
    {
      "member": "David P. Joyce",
      "positions": 9,
      "avgReturn": 0.6682605144425309
    },
    {
      "member": "Patrick J Toomey",
      "positions": 16,
      "avgReturn": 0.6649966838696006
    },
    {
      "member": "Andrew Garbarino",
      "positions": 2,
      "avgReturn": 0.6516860716602985
    },
    {
      "member": "Terri A. Sewell",
      "positions": 2,
      "avgReturn": 0.6417003986928622
    },
    {
      "member": "Scott Franklin",
      "positions": 47,
      "avgReturn": 0.6313934886976725
    },
    {
      "member": "Jerry Moran,",
      "positions": 53,
      "avgReturn": 0.6304898189078328
    },
    {
      "member": "Blake Moore",
      "positions": 68,
      "avgReturn": 0.6235660725517046
    },
    {
      "member": "John Rutherford",
      "positions": 26,
      "avgReturn": 0.6214013756296707
    },
    {
      "member": "Kevin Hern",
      "positions": 413,
      "avgReturn": 0.612280832927746
    },
    {
      "member": "Brian Babin",
      "positions": 2,
      "avgReturn": 0.608900225729962
    },
    {
      "member": "David Madison Cawthorn",
      "positions": 15,
      "avgReturn": 0.5993597546425811
    },
    {
      "member": "James Comer",
      "positions": 26,
      "avgReturn": 0.5951949588829465
    },
    {
      "member": "Robert J. Wittman",
      "positions": 79,
      "avgReturn": 0.579414036066051
    },
    {
      "member": "David Kustoff",
      "positions": 9,
      "avgReturn": 0.5656531075745386
    },
    {
      "member": "John Curtis",
      "positions": 112,
      "avgReturn": 0.5598121357180421
    },
    {
      "member": "Shelley M Capito",
      "positions": 112,
      "avgReturn": 0.5576211082715412
    },
    {
      "member": "Michael Patrick Guest",
      "positions": 46,
      "avgReturn": 0.5389542362195929
    },
    {
      "member": "Vicente Gonzalez",
      "positions": 1,
      "avgReturn": 0.5332761718112036
    },
    {
      "member": "Lois Frankel",
      "positions": 227,
      "avgReturn": 0.5312557941106404
    },
    {
      "member": "Christopher L. Jacobs",
      "positions": 51,
      "avgReturn": 0.5082060746836133
    },
    {
      "member": "Richard W. Allen",
      "positions": 131,
      "avgReturn": 0.5081636883989494
    },
    {
      "member": "Dan Newhouse",
      "positions": 87,
      "avgReturn": 0.5056934883569281
    },
    {
      "member": "Aston Donald McEachin",
      "positions": 6,
      "avgReturn": 0.5004901256045285
    },
    {
      "member": "Greg Steube",
      "positions": 2,
      "avgReturn": 0.498881431767338
    },
    {
      "member": "Cheri Bustos",
      "positions": 1,
      "avgReturn": 0.48212041585742016
    },
    {
      "member": "Hakeem S. Jeffries",
      "positions": 3,
      "avgReturn": 0.47616367774905405
    },
    {
      "member": "Peter Welch",
      "positions": 4,
      "avgReturn": 0.4654453844320404
    },
    {
      "member": "Alan S. Lowenthal",
      "positions": 159,
      "avgReturn": 0.4644763592664052
    },
    {
      "member": "Adam Kinzinger",
      "positions": 10,
      "avgReturn": 0.46020003238728646
    },
    {
      "member": "Virginia Foxx",
      "positions": 362,
      "avgReturn": 0.4465235797196317
    },
    {
      "member": "Thomas R Carper",
      "positions": 232,
      "avgReturn": 0.4374725387842167
    },
    {
      "member": "Markwayne Mullin",
      "positions": 265,
      "avgReturn": 0.43442742545759583
    },
    {
      "member": "Roger W. Marshall",
      "positions": 12,
      "avgReturn": 0.4315462985327789
    },
    {
      "member": "Joe Courtney",
      "positions": 13,
      "avgReturn": 0.4142026019202685
    },
    {
      "member": "Mo Brooks",
      "positions": 14,
      "avgReturn": 0.40884219584849885
    },
    {
      "member": "William R. Keating",
      "positions": 82,
      "avgReturn": 0.40215661761192567
    },
    {
      "member": "Cindy Axne",
      "positions": 48,
      "avgReturn": 0.3900916760691953
    },
    {
      "member": "Kelly Louise Morrison",
      "positions": 12,
      "avgReturn": 0.3844999116413992
    },
    {
      "member": "Lloyd Doggett",
      "positions": 129,
      "avgReturn": 0.383862356763257
    },
    {
      "member": "Angus S King, Jr.",
      "positions": 31,
      "avgReturn": 0.37979767147616256
    },
    {
      "member": "Josh Gottheimer",
      "positions": 931,
      "avgReturn": 0.37811501687215654
    },
    {
      "member": "James E. Banks",
      "positions": 8,
      "avgReturn": 0.37354358228853973
    },
    {
      "member": "Gilbert Cisneros",
      "positions": 1042,
      "avgReturn": 0.3704065227061361
    },
    {
      "member": "Harold Dallas Rogers",
      "positions": 7,
      "avgReturn": 0.3632204478521408
    },
    {
      "member": "Thomas H Tuberville",
      "positions": 372,
      "avgReturn": 0.3621157631209668
    },
    {
      "member": "Gary C Peters",
      "positions": 18,
      "avgReturn": 0.3567370431042534
    },
    {
      "member": "Earl Blumenauer",
      "positions": 142,
      "avgReturn": 0.3479712556396142
    },
    {
      "member": "John Fetterman",
      "positions": 8,
      "avgReturn": 0.34554315416703846
    },
    {
      "member": "Debbie Dingell",
      "positions": 15,
      "avgReturn": 0.34293943308651315
    },
    {
      "member": "Steve Cohen",
      "positions": 15,
      "avgReturn": 0.3404599052175022
    },
    {
      "member": "James French Hill",
      "positions": 10,
      "avgReturn": 0.33561690704346614
    },
    {
      "member": "John N Kennedy",
      "positions": 1,
      "avgReturn": 0.31591448931116384
    },
    {
      "member": "Ashley Hinson Arenholz",
      "positions": 2,
      "avgReturn": 0.31512915129151287
    },
    {
      "member": "Laurel Lee",
      "positions": 5,
      "avgReturn": 0.3074377681776531
    },
    {
      "member": "Rob Bresnahan",
      "positions": 169,
      "avgReturn": 0.3071919894974801
    },
    {
      "member": "Charles J. Chuck Fleischmann",
      "positions": 47,
      "avgReturn": 0.30645150931663867
    },
    {
      "member": "Daniel Goldman",
      "positions": 344,
      "avgReturn": 0.30428351355195643
    },
    {
      "member": "Kathy Manning",
      "positions": 150,
      "avgReturn": 0.29942880216919315
    },
    {
      "member": "William Cassidy",
      "positions": 17,
      "avgReturn": 0.29203970332471885
    },
    {
      "member": "William R. Timmons",
      "positions": 4,
      "avgReturn": 0.2920271428357232
    },
    {
      "member": "Roger Williams",
      "positions": 9,
      "avgReturn": 0.2914827580625744
    },
    {
      "member": "Robert E. Latta",
      "positions": 18,
      "avgReturn": 0.2863916467135717
    },
    {
      "member": "Sara Jacobs",
      "positions": 4,
      "avgReturn": 0.28490860674770735
    },
    {
      "member": "Julia Letlow",
      "positions": 120,
      "avgReturn": 0.2798086818703622
    },
    {
      "member": "Rohit Khanna",
      "positions": 117,
      "avgReturn": 0.2664555861655667
    },
    {
      "member": "Donald Sternoff Beyer",
      "positions": 168,
      "avgReturn": 0.2638641108018292
    },
    {
      "member": "David Trone",
      "positions": 14,
      "avgReturn": 0.2506437986234945
    },
    {
      "member": "Tim Moore",
      "positions": 86,
      "avgReturn": 0.24747075696924728
    },
    {
      "member": "Richard Dean McCormick",
      "positions": 57,
      "avgReturn": 0.23300935081130367
    },
    {
      "member": "Patrick Fallon",
      "positions": 22,
      "avgReturn": 0.22244875838861217
    },
    {
      "member": "Jonathan Jackson",
      "positions": 99,
      "avgReturn": 0.21933054806333743
    },
    {
      "member": "Kathy Castor",
      "positions": 2,
      "avgReturn": 0.217348400157797
    },
    {
      "member": "Mikie Sherrill",
      "positions": 22,
      "avgReturn": 0.2012678508341345
    },
    {
      "member": "Jared Moskowitz",
      "positions": 214,
      "avgReturn": 0.19971688158475162
    },
    {
      "member": "Fred Upton",
      "positions": 4,
      "avgReturn": 0.1898034943314833
    },
    {
      "member": "James R. Langevin",
      "positions": 80,
      "avgReturn": 0.1818672246996136
    },
    {
      "member": "Ed Case",
      "positions": 11,
      "avgReturn": 0.17717405966624608
    },
    {
      "member": "Thomas H. Kean",
      "positions": 52,
      "avgReturn": 0.1766217915464327
    },
    {
      "member": "Cleo Fields",
      "positions": 172,
      "avgReturn": 0.17104238313313389
    },
    {
      "member": "Peter Allen Stauber",
      "positions": 1,
      "avgReturn": 0.16490486257928105
    },
    {
      "member": "Byron Donalds",
      "positions": 40,
      "avgReturn": 0.1643185170809942
    },
    {
      "member": "Jefferson Shreve",
      "positions": 125,
      "avgReturn": 0.1584472222599227
    },
    {
      "member": "Katherine M. Clark",
      "positions": 44,
      "avgReturn": 0.1584340437424986
    },
    {
      "member": "Rick Larsen",
      "positions": 36,
      "avgReturn": 0.15569478285282454
    },
    {
      "member": "Maria Elvira Salazar",
      "positions": 44,
      "avgReturn": 0.1441419827571268
    },
    {
      "member": "Cynthia M Lummis",
      "positions": 1,
      "avgReturn": 0.13992153932374363
    },
    {
      "member": "Suzan K. DelBene",
      "positions": 14,
      "avgReturn": 0.1378295606775523
    },
    {
      "member": "Julie Johnson",
      "positions": 60,
      "avgReturn": 0.1320009149496028
    },
    {
      "member": "Roy Blunt",
      "positions": 1,
      "avgReturn": 0.12594458438287148
    },
    {
      "member": "John Boozman",
      "positions": 215,
      "avgReturn": 0.1105851453461639
    },
    {
      "member": "Cliff Bentz",
      "positions": 2,
      "avgReturn": 0.10811433202769888
    },
    {
      "member": "Kim Schrier",
      "positions": 2,
      "avgReturn": 0.097717284950814
    },
    {
      "member": "Ritchie John Torres",
      "positions": 48,
      "avgReturn": 0.07009514782624747
    },
    {
      "member": "C. Scott Franklin",
      "positions": 35,
      "avgReturn": 0.0654236373549863
    },
    {
      "member": "James M Inhofe",
      "positions": 6,
      "avgReturn": 0.06064071383708747
    },
    {
      "member": "Bruce Westerman",
      "positions": 70,
      "avgReturn": 0.05923406131654677
    },
    {
      "member": "David J. Taylor",
      "positions": 93,
      "avgReturn": 0.0572771351477935
    },
    {
      "member": "John James",
      "positions": 119,
      "avgReturn": 0.05626991239651458
    },
    {
      "member": "Lisa McClain",
      "positions": 533,
      "avgReturn": 0.05615843929931034
    },
    {
      "member": "August Lee Pfluger",
      "positions": 7,
      "avgReturn": 0.050738717687052626
    },
    {
      "member": "Lindsey Graham",
      "positions": 7,
      "avgReturn": 0.04670046949653682
    },
    {
      "member": "Scott Scott Franklin",
      "positions": 39,
      "avgReturn": 0.0405588808677609
    },
    {
      "member": "Michael Garcia",
      "positions": 17,
      "avgReturn": 0.02257373652436813
    },
    {
      "member": "Katie Britt",
      "positions": 16,
      "avgReturn": 0.020504532512732113
    },
    {
      "member": "Zoe Lofgren",
      "positions": 111,
      "avgReturn": 0.019738385293514318
    },
    {
      "member": "Marie Newman",
      "positions": 125,
      "avgReturn": 0.01769262515481434
    },
    {
      "member": "Daniel Crenshaw",
      "positions": 11,
      "avgReturn": 0.016177649604720488
    },
    {
      "member": "Greg Landsman",
      "positions": 53,
      "avgReturn": 0.015401184857508493
    },
    {
      "member": "Doug Lamborn",
      "positions": 34,
      "avgReturn": 0.013962456843501699
    },
    {
      "member": "Valerie Hoyle",
      "positions": 169,
      "avgReturn": 0.01133622835970949
    },
    {
      "member": "Abigail Spanberger",
      "positions": 2,
      "avgReturn": 0.009564494750677666
    },
    {
      "member": "Greg Stanton",
      "positions": 89,
      "avgReturn": 0.002255828574050211
    },
    {
      "member": "Justin Amash",
      "positions": 2,
      "avgReturn": 0.0012872561639767355
    },
    {
      "member": "Thomas R. Suozzi",
      "positions": 1,
      "avgReturn": 0
    },
    {
      "member": "Harley E. Rouda",
      "positions": 1,
      "avgReturn": 0
    },
    {
      "member": "Tom Rice",
      "positions": 1,
      "avgReturn": 0
    },
    {
      "member": "Tim Walberg",
      "positions": 13,
      "avgReturn": -0.005836608442240099
    },
    {
      "member": "Michael C. Burgess",
      "positions": 34,
      "avgReturn": -0.012226841932575139
    },
    {
      "member": "Sheri Biggs",
      "positions": 40,
      "avgReturn": -0.014809372602615995
    },
    {
      "member": "Raúl M. Grijalva",
      "positions": 2,
      "avgReturn": -0.014985380116959046
    },
    {
      "member": "April McClain Delaney",
      "positions": 159,
      "avgReturn": -0.018531923102576724
    },
    {
      "member": "Anthony E. Gonzalez",
      "positions": 3,
      "avgReturn": -0.02740593702267387
    },
    {
      "member": "Elaine Luria",
      "positions": 3,
      "avgReturn": -0.040379053882372805
    },
    {
      "member": "John W Hickenlooper",
      "positions": 29,
      "avgReturn": -0.05610993635515294
    },
    {
      "member": "William F Hagerty, IV",
      "positions": 1,
      "avgReturn": -0.06977235291633233
    },
    {
      "member": "John McGuire",
      "positions": 10,
      "avgReturn": -0.08566586435820649
    },
    {
      "member": "Chip Roy",
      "positions": 2,
      "avgReturn": -0.09378596087456836
    },
    {
      "member": "Ron Estes",
      "positions": 5,
      "avgReturn": -0.1090446926226474
    },
    {
      "member": "James E Banks",
      "positions": 16,
      "avgReturn": -0.10920132406156954
    },
    {
      "member": "Austin Scott",
      "positions": 32,
      "avgReturn": -0.15908002524080747
    },
    {
      "member": "Tom Malinowski",
      "positions": 26,
      "avgReturn": -0.16496124431852913
    },
    {
      "member": "David H McCormick",
      "positions": 24,
      "avgReturn": -0.32198285818164
    },
    {
      "member": "Felix Barry Moore",
      "positions": 5,
      "avgReturn": -0.4211438333621767
    },
    {
      "member": "Brandon Gill",
      "positions": 2,
      "avgReturn": -0.4797869276773174
    },
    {
      "member": "Brian Mast",
      "positions": 3,
      "avgReturn": -0.581721868278472
    },
    {
      "member": "Tom Cole",
      "positions": 1,
      "avgReturn": -0.8857142857142857
    }
  ]
}